cdm/__init__.py
cdm/enums/__init__.py
cdm/enums/cdm_attribute_context_type.py
cdm/enums/cdm_data_format.py
cdm/enums/cdm_object_type.py
cdm/enums/cdm_operation_type.py
cdm/enums/cdm_relationship_discovery_style.py
cdm/enums/cdm_status_level.py
cdm/enums/cdm_validation_step.py
cdm/enums/imports_load_strategy.py
cdm/objectmodel/__init__.py
cdm/objectmodel/_document_library.py
cdm/objectmodel/cdm_argument_collection.py
cdm/objectmodel/cdm_argument_def.py
cdm/objectmodel/cdm_argument_value.py
cdm/objectmodel/cdm_attribute_context.py
cdm/objectmodel/cdm_attribute_context_ref.py
cdm/objectmodel/cdm_attribute_def.py
cdm/objectmodel/cdm_attribute_group_def.py
cdm/objectmodel/cdm_attribute_group_ref.py
cdm/objectmodel/cdm_attribute_item.py
cdm/objectmodel/cdm_attribute_ref.py
cdm/objectmodel/cdm_attribute_resolution_guidance_def.py
cdm/objectmodel/cdm_collection.py
cdm/objectmodel/cdm_constant_entity_def.py
cdm/objectmodel/cdm_container_def.py
cdm/objectmodel/cdm_corpus_context.py
cdm/objectmodel/cdm_corpus_def.py
cdm/objectmodel/cdm_data_partition_def.py
cdm/objectmodel/cdm_data_partition_pattern_def.py
cdm/objectmodel/cdm_data_type_def.py
cdm/objectmodel/cdm_data_type_ref.py
cdm/objectmodel/cdm_definition_collection.py
cdm/objectmodel/cdm_document_collection.py
cdm/objectmodel/cdm_document_def.py
cdm/objectmodel/cdm_e2e_relationship.py
cdm/objectmodel/cdm_entity_attribute_def.py
cdm/objectmodel/cdm_entity_collection.py
cdm/objectmodel/cdm_entity_declaration_def.py
cdm/objectmodel/cdm_entity_def.py
cdm/objectmodel/cdm_entity_ref.py
cdm/objectmodel/cdm_file_status.py
cdm/objectmodel/cdm_folder_collection.py
cdm/objectmodel/cdm_folder_def.py
cdm/objectmodel/cdm_import.py
cdm/objectmodel/cdm_import_collection.py
cdm/objectmodel/cdm_local_entity_declaration_def.py
cdm/objectmodel/cdm_make_object.py
cdm/objectmodel/cdm_manifest_declaration_def.py
cdm/objectmodel/cdm_manifest_def.py
cdm/objectmodel/cdm_object.py
cdm/objectmodel/cdm_object_def.py
cdm/objectmodel/cdm_object_ref.py
cdm_connector_1.1-0.0.4.dist-info/LICENSE
cdm_connector_1.1-0.0.4.dist-info/METADATA
cdm_connector_1.1-0.0.4.dist-info/WHEEL
cdm_connector_1.1-0.0.4.dist-info/top_level.txt
cdm_connector_1.1-0.0.4.dist-info/RECORD
